aiomes/__init__.py
aiomes/errors.py
aiomes/main.py
aiomes/output_types.py
aiomes/user_auth.py
aiomes/utils.py
aiomes-1.5.2.dist-info/METADATA
aiomes-1.5.2.dist-info/WHEEL
aiomes-1.5.2.dist-info/top_level.txt
aiomes-1.5.2.dist-info/RECORD
