Metadata-Version: 2.1
Name: aiomes
Version: 1.5.2
Summary: Ассинхронная Python-библиотека с легким доступом к сервису МЭШ, написанная на aiohttp и async_playwright
Author-email: kester4 <forblitzilya@gmail.com>
Project-URL: Homepage, https://github.com/kester4/aiomes
Project-URL: Issues, https://github.com/kester4/aiomes/issues
Classifier: Programming Language :: Python :: 3
Classifier: Operating System :: OS Independent
Requires-Python: >=3.12
Requires-Dist: playwright
Requires-Dist: aiohttp
Requires-Dist: async-class
Requires-Dist: pydantic
